<?xml version="1.0" encoding="utf-8"?>
<!DOCTYPE hibernate-mapping PUBLIC "-//Hibernate/Hibernate Mapping DTD 3.0//EN"
        "http://www.hibernate.org/dtd/hibernate-mapping-3.0.dtd">
<!-- 
    Mapping file autogenerated by MyEclipse Persistence Tools
-->
<hibernate-mapping>
    <class name="com.yufan.pojo.TbParam" table="tb_param" catalog="rs_database">
        <id name="paramId" type="integer">
            <column name="param_id"/>
            <generator class="native"/>
        </id>
        <property name="paramName" type="string">
            <column name="param_name" length="40">
                <comment>名称</comment>
            </column>
        </property>
        <property name="paramType" type="string">
            <column name="param_type" length="10"/>
        </property>
        <property name="paramCode" type="string">
            <column name="param_code" length="100">
                <comment>编码</comment>
            </column>
        </property>
        <property name="paramKey" type="string">
            <column name="param_key" length="100"/>
        </property>
        <property name="paramValue" type="string">
            <column name="param_value" length="200">
                <comment>参数值</comment>
            </column>
        </property>
        <property name="paramValue1" type="string">
            <column name="param_value1" length="200">
                <comment>参数值1</comment>
            </column>
        </property>
        <property name="paramValue2" type="string">
            <column name="param_value2" length="200"/>
        </property>
        <property name="createman" type="string">
            <column name="createman" length="100"/>
        </property>
        <property name="createtime" type="timestamp">
            <column name="createtime" length="19"/>
        </property>
        <property name="lastaltertime" type="timestamp">
            <column name="lastaltertime" length="19"/>
        </property>
        <property name="lastalterman" type="string">
            <column name="lastalterman" length="100"/>
        </property>
        <property name="status" type="integer">
            <column name="status">
                <comment>0无效1有效2冻结(管理员)3删除(管理员)</comment>
            </column>
        </property>
        <property name="remark" type="string">
            <column name="remark" length="200"/>
        </property>
        <property name="isMakeSure" type="integer">
            <column name="is_make_sure">
                <comment>需要确认0等待确认1已确认</comment>
            </column>
        </property>
    </class>
</hibernate-mapping>
